{
	"eId": "0",
	"type": 0,
	"desp": "There is a sound beyond the mist.",
	"stages": {
		"2": {
			"sId": 2,
			"desp": "“You are trapped, my cutie pie.”\nThe pale lady smirks.",
			"stageType": 0,
			"res": null,
			"randomValue": 0,
			"battleRes": 0,
			"extra":"monster",
			"converts": [{
				"nextStageIdx": 5,
				"choiceDesp": "Fight",
				"checks": []
			}]
		},
		"1": {
			"sId": 1,
			"desp": "She slowly moves towards you.",
			"stageType": 0,
			"res": null,
			"randomValue": 0,
			"battleRes": 0,
			"converts": [{
					"nextStageIdx": 3,
					"choiceDesp": "Stay still",
					"checks": []
				},
				{
					"nextStageIdx": 4,
					"choiceDesp": "Use a quest",
					"checks": [{
							"key": "san",
							"fuhao": 2,
							"value": "90"
						},
						{
							"key": "",
							"fuhao": 0,
							"value": ""
						}
					]
				}
			]
		},
		"0": {
			"sId": 0,
			"desp": "The pale lady is in front of you. \nHer eyes look empty , yet her lips are shimmering.\nYou feel like looking into the mirror when you look in her eyes.",
			"stageType": 0,
			"res": null,
			"randomValue": 0,
			"battleRes": 0,
			"converts": [{
					"nextStageIdx": 1,
					"choiceDesp": "Step ahead",
					"checks": []
				},
				{
					"nextStageIdx": 2,
					"choiceDesp": "Run away",
					"checks": []
				}
			]
		},
		"3": {
			"sId": 3,
			"desp": "“Where are you from?”\nThe pale lady asks.",
			"stageType": 0,
			"res": null,
			"randomValue": 0,
			"battleRes": 0,
			"converts": [{
					"nextStageIdx": 10,
					"choiceDesp": "Remain silent",
					"checks": []
				},
				{
					"nextStageIdx": 9,
					"choiceDesp": "Use a spell",
					"checks": []
				}
			]
		},
		"4": {
			"sId": 4,
			"desp": "The pale lady was dazzled by a flash. \nYou noticed the vampire fangs in her mouth.",
			"stageType": 0,
			"res": null,
			"randomValue": 0,
			"battleRes": 0,
			"converts": [{
				"nextStageIdx": 8,
				"choiceDesp": "Run away",
				"checks": []
			}]
		},
		"5": {
			"sId": 5,
			"desp": "Fight on!",
			"stageType": 1,
			"res": null,
			"randomValue": 0,
			"battleRes": 0,
			"converts": [{
					"nextStageIdx": 6,
					"choiceDesp": "描述符",
					"checks": [{
						"key": "win",
						"fuhao": 1,
						"value": "true"
					}]
				},
				{
					"nextStageIdx": 7,
					"choiceDesp": "描述符",
					"checks": [{
						"key": "win",
						"fuhao": 1,
						"value": "false"
					}]
				}
			]
		},
		"6": {
			"sId": 6,
			"desp": "You won this round, but you have not won the game named life yet.",
			"stageType": 0,
			"res": null,
			"randomValue": 0,
			"battleRes": 0,
			"converts": [{
				"nextStageIdx": 13,
				"choiceDesp": "(Close)",
				"checks": []
			}]
		},
		"7": {
			"sId": 7,
			"desp": "You have earned an one-way trip to hell.",
			"stageType": 0,
			"res": null,
			"randomValue": 0,
			"battleRes": 0,
			"converts": [{
				"nextStageIdx": 14,
				"choiceDesp": "(Close)",
				"checks": []
			}]
		},
		"8": {
			"sId": 8,
			"desp": "check",
			"stageType": 4,
			"res": null,
			"randomValue": 0,
			"battleRes": 0,
			"converts": [{
					"nextStageIdx": 11,
					"choiceDesp": "random",
					"checks": [{
						"key": "random",
						"fuhao": 2,
						"value": "70"
					}]
				},
				{
					"nextStageIdx": 12,
					"choiceDesp": "random",
					"checks": [{
						"key": "random",
						"fuhao": 3,
						"value": "70"
					}]
				}
			]
		},
		"9": {
			"sId": 9,
			"desp": "",
			"stageType": 3,
			"res": {
				"type": 0,
				"finishEffect": "none",
				"rewords": [{
						"rewardName": "",
						"rewardAmount": 0,
						"chance": 0
					},
					{
						"rewardName": "",
						"rewardAmount": 0,
						"chance": 0
					}
				]
			},
			"randomValue": 0,
			"battleRes": 0,
			"converts": []
		},
		"10": {
			"sId": 10,
			"desp": "",
			"stageType": 3,
			"res": {
				"type": 0,
				"finishEffect": "none",
				"rewords": [{
					"rewardName": "",
					"rewardAmount": 0,
					"chance": 0
				}]
			},
			"randomValue": 0,
			"battleRes": 0,
			"converts": []
		},
		"11": {
			"sId": 11,
			"desp": "You escaped.",
			"stageType": 0,
			"res": null,
			"randomValue": 0,
			"battleRes": 0,
			"converts": [{
				"nextStageIdx": 15,
				"choiceDesp": "(Close)",
				"checks": []
			}]
		},
		"12": {
			"sId": 12,
			"desp": "The pale lady trapped you. \nYou and her live happily ever after.",
			"stageType": 0,
			"res": null,
			"randomValue": 0,
			"battleRes": 0,
			"converts": [{
				"nextStageIdx": 16,
				"choiceDesp": "(Close)",
				"checks": []
			}]
		},
		"13": {
			"sId": 13,
			"desp": "",
			"stageType": 3,
			"res": {
				"type": 0,
				"finishEffect": "none",
				"rewords": []
			},
			"randomValue": 0,
			"battleRes": 0,
			"converts": []
		},
		"14": {
			"sId": 14,
			"desp": "",
			"stageType": 3,
			"res": {
				"type": 0,
				"finishEffect": "none",
				"rewords": []
			},
			"randomValue": 0,
			"battleRes": 0,
			"converts": []
		},
		"15": {
			"sId": 15,
			"desp": "",
			"stageType": 3,
			"res": {
				"type": 0,
				"finishEffect": "none",
				"rewords": [{
						"rewardName": "",
						"rewardAmount": 0,
						"chance": 0
					},
					{
						"rewardName": "",
						"rewardAmount": 0,
						"chance": 0
					}
				]
			},
			"randomValue": 0,
			"battleRes": 0,
			"converts": []
		},
		"16": {
			"sId": 16,
			"desp": "",
			"stageType": 3,
			"res": {
				"type": 0,
				"finishEffect": "none",
				"rewords": []
			},
			"randomValue": 0,
			"battleRes": 0,
			"converts": []
		}
	}

}